table_data_reader/__init__.py
table_data_reader/__main__.py
table_data_reader/cli.py
table_data_reader/table_data_writer.py
eam_data_tools-1.5.0.dist-info/LICENSE
eam_data_tools-1.5.0.dist-info/METADATA
eam_data_tools-1.5.0.dist-info/WHEEL
eam_data_tools-1.5.0.dist-info/entry_points.txt
eam_data_tools-1.5.0.dist-info/top_level.txt
eam_data_tools-1.5.0.dist-info/RECORD
