Metadata-Version: 2.1
Name: eam-data-tools
Version: 1.5.0
Summary: Tool to read model data from a table
Home-page: https://github.com/dschien/eam-data-tools
Author: Dan Schien
Author-email: daniel.schien@bristol.ac.uk
License: Apache-2.0
Project-URL: Documentation, https://eam-data-tools.readthedocs.io/
Project-URL: Changelog, https://eam-data-tools.readthedocs.io/en/latest/changelog.html
Project-URL: Issue Tracker, https://github.com/dschien/eam-data-tools/issues
Platform: UNKNOWN
Classifier: Development Status :: 5 - Production/Stable
Classifier: Intended Audience :: Developers
Classifier: License :: OSI Approved :: Apache Software License
Classifier: Operating System :: Unix
Classifier: Operating System :: POSIX
Classifier: Operating System :: Microsoft :: Windows
Classifier: Programming Language :: Python
Classifier: Programming Language :: Python :: 3.6
Classifier: Programming Language :: Python :: 3.7
Classifier: Programming Language :: Python :: 3.8
Classifier: Topic :: Utilities
Requires-Python: >=3.6
Requires-Dist: openpyxl
Requires-Dist: scipy
Requires-Dist: xlrd
Requires-Dist: pandas (==0.24.2)
Requires-Dist: pint
Requires-Dist: pint-pandas-fork
Requires-Dist: numpy
Requires-Dist: python-dateutil
Provides-Extra: excel
Requires-Dist: openpyxl ; extra == 'excel'
Requires-Dist: xlrd ; extra == 'excel'
Provides-Extra: test
Requires-Dist: pytest ; extra == 'test'
Requires-Dist: pytest-cov ; extra == 'test'
Requires-Dist: codecov ; extra == 'test'
Requires-Dist: coveralls ; extra == 'test'
Requires-Dist: nbval ; extra == 'test'
Provides-Extra: units
